odoo8_addon_l10n_es_aeat_mod130-8.0.0.9.0-py2.7-nspkg.pth
odoo8_addon_l10n_es_aeat_mod130-8.0.0.9.0.dist-info/DESCRIPTION.rst
odoo8_addon_l10n_es_aeat_mod130-8.0.0.9.0.dist-info/METADATA
odoo8_addon_l10n_es_aeat_mod130-8.0.0.9.0.dist-info/RECORD
odoo8_addon_l10n_es_aeat_mod130-8.0.0.9.0.dist-info/WHEEL
odoo8_addon_l10n_es_aeat_mod130-8.0.0.9.0.dist-info/metadata.json
odoo8_addon_l10n_es_aeat_mod130-8.0.0.9.0.dist-info/namespace_packages.txt
odoo8_addon_l10n_es_aeat_mod130-8.0.0.9.0.dist-info/top_level.txt
odoo_addons/l10n_es_aeat_mod130/__init__.py
odoo_addons/l10n_es_aeat_mod130/__openerp__.py
odoo_addons/l10n_es_aeat_mod130/doc/BOE especification.pdf
odoo_addons/l10n_es_aeat_mod130/doc/Instrucciones.pdf
odoo_addons/l10n_es_aeat_mod130/i18n/bg.po
odoo_addons/l10n_es_aeat_mod130/i18n/ca.po
odoo_addons/l10n_es_aeat_mod130/i18n/cs.po
odoo_addons/l10n_es_aeat_mod130/i18n/es.po
odoo_addons/l10n_es_aeat_mod130/i18n/es_CO.po
odoo_addons/l10n_es_aeat_mod130/i18n/es_CR.po
odoo_addons/l10n_es_aeat_mod130/i18n/eu.po
odoo_addons/l10n_es_aeat_mod130/i18n/fr.po
odoo_addons/l10n_es_aeat_mod130/i18n/gl.po
odoo_addons/l10n_es_aeat_mod130/i18n/hr.po
odoo_addons/l10n_es_aeat_mod130/i18n/l10n_es_aeat_mod130.pot
odoo_addons/l10n_es_aeat_mod130/i18n/nl.po
odoo_addons/l10n_es_aeat_mod130/i18n/pl.po
odoo_addons/l10n_es_aeat_mod130/i18n/pt.po
odoo_addons/l10n_es_aeat_mod130/i18n/pt_BR.po
odoo_addons/l10n_es_aeat_mod130/i18n/ru.po
odoo_addons/l10n_es_aeat_mod130/i18n/sl.po
odoo_addons/l10n_es_aeat_mod130/i18n/sv.po
odoo_addons/l10n_es_aeat_mod130/i18n/tr.po
odoo_addons/l10n_es_aeat_mod130/i18n/vi.po
odoo_addons/l10n_es_aeat_mod130/models/__init__.py
odoo_addons/l10n_es_aeat_mod130/models/mod130.py
odoo_addons/l10n_es_aeat_mod130/security/ir.model.access.csv
odoo_addons/l10n_es_aeat_mod130/security/ir_rule.xml
odoo_addons/l10n_es_aeat_mod130/static/description/icon.png
odoo_addons/l10n_es_aeat_mod130/static/description/icon_source.svg
odoo_addons/l10n_es_aeat_mod130/views/mod130_view.xml
odoo_addons/l10n_es_aeat_mod130/wizard/__init__.py
odoo_addons/l10n_es_aeat_mod130/wizard/export_mod130_to_boe.py
odoo_addons/l10n_es_aeat_mod130/wizard/export_mod130_to_boe.xml
