Metadata-Version: 2.0
Name: odoo8-addon-l10n-es-aeat-mod130
Version: 8.0.0.9.0
Summary: AEAT modelo 130
Home-page: http://www.serviciosbaeza.com
Author: Serv. Tecnol. Avanzados - Pedro M. Baeza, Odoo Community Association (OCA)
Author-email: support@odoo-community.org
License: AGPL-3
Platform: UNKNOWN
Classifier: Programming Language :: Python :: 2.7
Classifier: Framework :: Odoo
Classifier: License :: OSI Approved :: GNU Affero General Public License v3
Requires-Dist: odoo (<9.0a,>=8.0a)
Requires-Dist: odoo8-addon-l10n-es-aeat
